{
  "backdrop_path": "https://image.tmdb.org/t/p/w500/hpgda6P9GutvdkDX5MUJ92QG9aj.jpg",
  "id": 384018,
  "title": "Fast & Furious Presents: Hobbs & Shaw",
  "poster_path": "https://image.tmdb.org/t/p/w500/qRyy2UmjC5ur9bDi3kpNNRCc5nc.jpg",
  "release_date": "2019-08-01",
  "vote_average": 6.866,
  "vote_count": 6793,
  "popularity": 112.771,
  "overview": "Ever since US Diplomatic Security Service Agent Hobbs and lawless outcast Shaw first faced off, they just have traded smack talk and body blows. But when cyber-genetically enhanced anarchist Brixton's ruthless actions threaten the future of humanity, they join forces to defeat him.",
  "imdb_id": "tt6806448",
  "budget": 200000000,
  "homepage": "https://www.uphe.com/movies/fast-furious-presents-hobbs-shaw",
  "revenue": 760098996,
  "runtime": 137,
  "tagline": "Nothing is stronger than family.",
  "genres": [
    "Action",
    "Adventure",
    "Comedy"
  ],
  "production_companies": [
    "Chris Morgan Productions",
    "Seven Bucks Productions",
    "Universal Pictures"
  ],
  "production_countries": [
    "US"
  ],
  "credits": {
    "cast": [
      {
        "name": "Dwayne Johnson",
        "character": "Luke Hobbs"
      },
      {
        "name": "Jason Statham",
        "character": "Deckard Shaw"
      },
      {
        "name": "Idris Elba",
        "character": "Brixton"
      },
      {
        "name": "Vanessa Kirby",
        "character": "Hattie Shaw"
      },
      {
        "name": "Helen Mirren",
        "character": "Queenie Shaw"
      },
      {
        "name": "Eiza González",
        "character": "Madame M"
      },
      {
        "name": "Eddie Marsan",
        "character": "Professor Andreiko"
      },
      {
        "name": "Eliana Su'a",
        "character": "Sam Hobbs"
      },
      {
        "name": "Cliff Curtis",
        "character": "Jonah Hobbs"
      },
      {
        "name": "Lori Pelenise Tuisano",
        "character": "Sefina"
      },
      {
        "name": "John Tui",
        "character": "Kal"
      },
      {
        "name": "Joshua Mauga",
        "character": "Timo"
      },
      {
        "name": "Joe Anoa'i",
        "character": "Mateo"
      },
      {
        "name": "Rob Delaney",
        "character": "Agent Loeb"
      },
      {
        "name": "Alex King",
        "character": "Lt. Grapefruit"
      },
      {
        "name": "Tom Wu",
        "character": "Tsoi"
      },
      {
        "name": "John Macdonald",
        "character": "Lermotov"
      },
      {
        "name": "Georgia Meacham",
        "character": "Party Model #1"
      },
      {
        "name": "Laura Porta",
        "character": "Party Model #2"
      },
      {
        "name": "Ima Caryl",
        "character": "Tattoo Assistant"
      },
      {
        "name": "Shiloh Coke",
        "character": "Prison Guard"
      },
      {
        "name": "Joshua Coombes",
        "character": "Young Deckard"
      },
      {
        "name": "Meesha Garbett",
        "character": "Young Hattie"
      },
      {
        "name": "Harry Hickles",
        "character": "Young Owen"
      },
      {
        "name": "Lucy McCormick",
        "character": "L.A. Waitress"
      },
      {
        "name": "Stephen Mitchell",
        "character": "CIA Handler #1"
      },
      {
        "name": "Akie Kotabe",
        "character": "CIA Handler #2"
      },
      {
        "name": "Felicity Dean",
        "character": "Savoy Check-in Guest"
      },
      {
        "name": "Pete White",
        "character": "London Cabbie"
      },
      {
        "name": "Peter Basham",
        "character": "Agent at Hattie's #1"
      },
      {
        "name": "Noah Maxwell Clarke",
        "character": "Agent at Hattie's #2"
      },
      {
        "name": "Joel MacCormack",
        "character": "CIA Mapping Agent"
      },
      {
        "name": "Vineeta Rishi",
        "character": "Eteon Assistant"
      },
      {
        "name": "Ryan Reynolds",
        "character": "Eteon Director / Victor Locke"
      },
      {
        "name": "David Mumeni",
        "character": "Eteon Computer Tech"
      },
      {
        "name": "Gavin Esler",
        "character": "U.K. Newsreader #1"
      },
      {
        "name": "Ansu Kabia",
        "character": "U.K. Newsreader #2"
      },
      {
        "name": "Stephanie Vogt",
        "character": "U.S. Newsreader"
      },
      {
        "name": "Dan Li",
        "character": "Chinese Newsreader"
      },
      {
        "name": "Adam Ganne",
        "character": "German Newsreader"
      },
      {
        "name": "Antonio Mancino",
        "character": "Italian Newsreader"
      },
      {
        "name": "Dan H. McCormick",
        "character": "Paper Boy"
      },
      {
        "name": "Thalissa Teixeira",
        "character": "Rosie's Nanny"
      },
      {
        "name": "James Dryden",
        "character": "British Custom Officer"
      },
      {
        "name": "Katia Elizarova",
        "character": "Flight Attendant"
      },
      {
        "name": "Ella-Rae Smith",
        "character": "Madame M's Crew #1"
      },
      {
        "name": "Rain Chan",
        "character": "Madame M's Crew #2"
      },
      {
        "name": "Lee Anne Nyagodzi",
        "character": "Madame M's Crew #3"
      },
      {
        "name": "Maria Sergejeva",
        "character": "Madame M's Crew #4"
      },
      {
        "name": "Mackenzie Proll",
        "character": "Young Bully #1"
      },
      {
        "name": "Jack Kane",
        "character": "Young Bully #2"
      },
      {
        "name": "Nathan Jones",
        "character": "Russian Fighter Pilot"
      },
      {
        "name": "Spencer Wilding",
        "character": "Eteon's Uber Merc"
      },
      {
        "name": "Axel Nu",
        "character": "Eteon Medical Tech"
      },
      {
        "name": "Stephen Dunlevy",
        "character": "Eteon Merc #1"
      },
      {
        "name": "Timothy Connolly",
        "character": "Eteon Merc #2"
      },
      {
        "name": "David Leitch",
        "character": "Eteon Helicopter Pilot"
      },
      {
        "name": "Michael Wildman",
        "character": "U.K. Police Leader"
      },
      {
        "name": "Jobe Allen",
        "character": "Samoan Local (uncredited)"
      },
      {
        "name": "Manoj Anand",
        "character": "Airport Passenger (uncredited)"
      },
      {
        "name": "Lasco Atkins",
        "character": "Construction Worker (uncredited)"
      },
      {
        "name": "Pualani Avaeoru",
        "character": "Spouse (uncredited)"
      },
      {
        "name": "Leo Ayres",
        "character": "Gang Member (uncredited)"
      },
      {
        "name": "Philip John Bailey",
        "character": "Soldier (uncredited)"
      },
      {
        "name": "Lyon Beckwith",
        "character": "Hobb's Cousin (uncredited)"
      },
      {
        "name": "Daniel Bernhardt",
        "character": "Henchman (uncredited)"
      },
      {
        "name": "Kishore Bhatt",
        "character": "Airport Passenger (uncredited)"
      },
      {
        "name": "Martin Bratanov",
        "character": "Kitchen Porter (uncredited)"
      },
      {
        "name": "Sergio Briones",
        "character": "Mercenary (uncredited)"
      },
      {
        "name": "Jill Buchanan",
        "character": "Prison Visitor (uncredited)"
      },
      {
        "name": "Abbey Butler",
        "character": "Airport Steward (uncredited)"
      },
      {
        "name": "Conlan Casal",
        "character": "Mercenary (uncredited)"
      },
      {
        "name": "Tim Connolly",
        "character": "Cocky Merc (uncredited)"
      },
      {
        "name": "Samantha Corcoran",
        "character": "Background Security (uncredited)"
      },
      {
        "name": "Richard Curtis",
        "character": "Bicycle Courier (uncredited)"
      },
      {
        "name": "James 'JD Knight' Dunn",
        "character": "Infantry Henchman (uncredited)"
      },
      {
        "name": "Daniel Eghan",
        "character": "Diner (uncredited)"
      },
      {
        "name": "Viktorija Faith",
        "character": "Russian Plane Passenger (uncredited)"
      },
      {
        "name": "Francesca Fraser",
        "character": "Wife Diner (uncredited)"
      },
      {
        "name": "Vikrem Singh",
        "character": "Airport Steward (uncredited)"
      },
      {
        "name": "Michel Alexandre Gonzalez",
        "character": "Hairdresser (uncredited)"
      },
      {
        "name": "Mark Gooden",
        "character": "Mechanic (uncredited)"
      },
      {
        "name": "Sonia Goswami",
        "character": "City Woman (uncredited)"
      },
      {
        "name": "Layne Hannemann",
        "character": "Hobbs' Cousin (uncredited)"
      },
      {
        "name": "Kevin Hart",
        "character": "Air Marshal Dinkley (uncredited)"
      },
      {
        "name": "Patrick Doran",
        "character": "Passerby (uncredited)"
      },
      {
        "name": "Ruth Clarson",
        "character": "City Woman (uncredited)"
      },
      {
        "name": "Kalanikauleleiaiwi Jardine",
        "character": "Auto Shop Worker (uncredited)"
      },
      {
        "name": "Kyle Justin Leatherberry",
        "character": "Mercenary (uncredited)"
      },
      {
        "name": "Westley LeClay",
        "character": "Hobbs' Cousin (uncredited)"
      },
      {
        "name": "Steven Lewington",
        "character": "Black Infantry Soldier (uncredited)"
      },
      {
        "name": "Marian Lorencik",
        "character": "Russian Plane Passenger (uncredited)"
      },
      {
        "name": "Teresa Mahoney",
        "character": "Lady in Rain (uncredited)"
      },
      {
        "name": "Stephen McGowan",
        "character": "Bio-Hazard Scientist (uncredited)"
      },
      {
        "name": "Peter Parker Mensah",
        "character": "Black Infantry Soldier (uncredited)"
      },
      {
        "name": "Kelemete Misipeka",
        "character": "Samoan War Dancer (uncredited)"
      },
      {
        "name": "Pingi Moli",
        "character": "Hobbs' Cousin (uncredited)"
      },
      {
        "name": "Richard James Montgomery",
        "character": "Mercenary / Talos Suit (uncredited)"
      },
      {
        "name": "Sascha Panknin",
        "character": "Airport Passenger (uncredited)"
      },
      {
        "name": "Hio Pelesasa",
        "character": "Hobbs Cousin (uncredited)"
      },
      {
        "name": "Peter Rooney",
        "character": "Pedestrian (uncredited)"
      },
      {
        "name": "Israel Ruiz",
        "character": "London City Worker (uncredited)"
      },
      {
        "name": "Rubens Saboia",
        "character": "Black Infantry Soldier (uncredited)"
      },
      {
        "name": "Ben-Hur Santos",
        "character": "Warehouse Engineer (uncredited)"
      },
      {
        "name": "Dave Simon",
        "character": "Security (uncredited)"
      },
      {
        "name": "David Sturgeon",
        "character": "Mercenary (uncredited)"
      },
      {
        "name": "Matt Symonds",
        "character": "Black infantry (uncredited)"
      },
      {
        "name": "Matt Townsend",
        "character": "City Man (uncredited)"
      },
      {
        "name": "Rutvig Vaid",
        "character": "International Tourist (uncredited)"
      },
      {
        "name": "Jay Waddell",
        "character": "Street Racer (uncredited)"
      },
      {
        "name": "Nicholas Walker",
        "character": "Mercenary (uncredited)"
      },
      {
        "name": "Ryan Bailey",
        "character": "Hector"
      },
      {
        "name": "Richard Price",
        "character": "Passerby (uncredited)"
      }
    ],
    "crew": [
      {
        "name": "Jason Statham",
        "department": "Production",
        "job": "Producer"
      },
      {
        "name": "Mary Vernieu",
        "department": "Production",
        "job": "Casting"
      },
      {
        "name": "Peter Brown",
        "department": "Sound",
        "job": "Sound Designer"
      },
      {
        "name": "Gary Scott Thompson",
        "department": "Writing",
        "job": "Characters"
      },
      {
        "name": "Tina Maskell",
        "department": "Crew",
        "job": "Stunts"
      },
      {
        "name": "Daniel Bernhardt",
        "department": "Crew",
        "job": "Stunts"
      },
      {
        "name": "David Leitch",
        "department": "Directing",
        "job": "Director"
      },
      {
        "name": "Matthew Stirling",
        "department": "Crew",
        "job": "Stunt Driver"
      },
      {
        "name": "Jonathan Sela",
        "department": "Camera",
        "job": "Director of Photography"
      },
      {
        "name": "Mike Mukatis",
        "department": "Crew",
        "job": "Stunts"
      },
      {
        "name": "Tyler Bates",
        "department": "Sound",
        "job": "Original Music Composer"
      },
      {
        "name": "Paul Pattison",
        "department": "Costume & Make-Up",
        "job": "Makeup Artist"
      },
      {
        "name": "Mark P. Stoeckinger",
        "department": "Sound",
        "job": "Sound Designer"
      },
      {
        "name": "Eddie J. Fernandez",
        "department": "Crew",
        "job": "Stunts"
      },
      {
        "name": "Dwayne Johnson",
        "department": "Production",
        "job": "Producer"
      },
      {
        "name": "Steve Chasman",
        "department": "Production",
        "job": "Executive Producer"
      },
      {
        "name": "Cyril Raffaelli",
        "department": "Crew",
        "job": "Stunts"
      },
      {
        "name": "Lucy Bevan",
        "department": "Production",
        "job": "Casting"
      },
      {
        "name": "Christopher Rouse",
        "department": "Editing",
        "job": "Editor"
      },
      {
        "name": "Simon McGuire",
        "department": "Art",
        "job": "Art Direction"
      },
      {
        "name": "Chris Palermo",
        "department": "Crew",
        "job": "Stunt Driver"
      },
      {
        "name": "Chris Morgan",
        "department": "Writing",
        "job": "Screenplay"
      },
      {
        "name": "Chris Morgan",
        "department": "Production",
        "job": "Producer"
      },
      {
        "name": "Chris Morgan",
        "department": "Writing",
        "job": "Story"
      },
      {
        "name": "Max Berman",
        "department": "Art",
        "job": "Concept Artist"
      },
      {
        "name": "Clay Cullen",
        "department": "Crew",
        "job": "Stunt Driver"
      },
      {
        "name": "Shane Vieau",
        "department": "Art",
        "job": "Set Decoration"
      },
      {
        "name": "Marvin Campbell",
        "department": "Crew",
        "job": "Stunts"
      },
      {
        "name": "David Allday",
        "department": "Art",
        "job": "Art Direction"
      },
      {
        "name": "Jalil Jay Lynch",
        "department": "Crew",
        "job": "Stunt Driver"
      },
      {
        "name": "Tanoai Reed",
        "department": "Crew",
        "job": "Stunt Double"
      },
      {
        "name": "Lisa Chugg",
        "department": "Art",
        "job": "Set Decoration"
      },
      {
        "name": "Loyd Bateman",
        "department": "Crew",
        "job": "Stunts"
      },
      {
        "name": "Simon Crane",
        "department": "Crew",
        "job": "Stunt Coordinator"
      },
      {
        "name": "Simon Crane",
        "department": "Directing",
        "job": "Second Unit Director"
      },
      {
        "name": "Freddy Bouciegues",
        "department": "Crew",
        "job": "Stunts"
      },
      {
        "name": "Antal Kalik",
        "department": "Crew",
        "job": "Stunts"
      },
      {
        "name": "Stanimir Stamatov",
        "department": "Crew",
        "job": "Stunts"
      },
      {
        "name": "Russell Balogh",
        "department": "Crew",
        "job": "Stunts"
      },
      {
        "name": "David Scheunemann",
        "department": "Art",
        "job": "Production Design"
      },
      {
        "name": "Dean Wolcott",
        "department": "Art",
        "job": "Set Designer"
      },
      {
        "name": "Ethan Smith",
        "department": "Production",
        "job": "Executive Producer"
      },
      {
        "name": "Ethan Smith",
        "department": "Production",
        "job": "Unit Production Manager"
      },
      {
        "name": "Kelly McCormick",
        "department": "Production",
        "job": "Executive Producer"
      },
      {
        "name": "Dany Garcia",
        "department": "Production",
        "job": "Executive Producer"
      },
      {
        "name": "Nicole Powell",
        "department": "Crew",
        "job": "Stunts"
      },
      {
        "name": "J.D. Schwalm",
        "department": "Visual Effects",
        "job": "Special Effects Supervisor"
      },
      {
        "name": "Paul Barry",
        "department": "Directing",
        "job": "First Assistant Director"
      },
      {
        "name": "Wolfgang Metschan",
        "department": "Art",
        "job": "Art Direction"
      },
      {
        "name": "Bruno Martins",
        "department": "Lighting",
        "job": "Electrician"
      },
      {
        "name": "Jeff Murrell",
        "department": "Lighting",
        "job": "Gaffer"
      },
      {
        "name": "Rashid Phoenix",
        "department": "Crew",
        "job": "Stunts"
      },
      {
        "name": "Drew Pearce",
        "department": "Writing",
        "job": "Screenplay"
      },
      {
        "name": "Tanner Foust",
        "department": "Crew",
        "job": "Stunt Driver"
      },
      {
        "name": "William Eliscu",
        "department": "Art",
        "job": "Assistant Art Director"
      },
      {
        "name": "Leon Sua",
        "department": "Crew",
        "job": "Stunts"
      },
      {
        "name": "Efka Kvaraciejus",
        "department": "Crew",
        "job": "Stunts"
      },
      {
        "name": "Shahaub Roudbari",
        "department": "Crew",
        "job": "Stunts"
      },
      {
        "name": "Clay Donahue Fontenot",
        "department": "Crew",
        "job": "Stunts"
      },
      {
        "name": "Stefan von Borbély",
        "department": "Camera",
        "job": "Camera Operator"
      },
      {
        "name": "Alessandro Bertolazzi",
        "department": "Costume & Make-Up",
        "job": "Makeup Designer"
      },
      {
        "name": "Jonathan Weber",
        "department": "Visual Effects",
        "job": "Visual Effects Supervisor"
      },
      {
        "name": "Ashley Winter",
        "department": "Art",
        "job": "Assistant Art Director"
      },
      {
        "name": "Mats Andersen",
        "department": "Visual Effects",
        "job": "Visual Effects Producer"
      },
      {
        "name": "Scott R. Fisher",
        "department": "Crew",
        "job": "Stunts"
      },
      {
        "name": "Laura Swift",
        "department": "Crew",
        "job": "Stunt Double"
      },
      {
        "name": "Stuart Lashley",
        "department": "Visual Effects",
        "job": "Visual Effects Supervisor"
      },
      {
        "name": "Will Coubrough",
        "department": "Art",
        "job": "Art Direction"
      },
      {
        "name": "Kim Phelan",
        "department": "Visual Effects",
        "job": "Visual Effects Producer"
      },
      {
        "name": "Frank Masi",
        "department": "Camera",
        "job": "Still Photographer"
      },
      {
        "name": "Marylou Lim",
        "department": "Costume & Make-Up",
        "job": "Costumer"
      },
      {
        "name": "Julie Brown",
        "department": "Directing",
        "job": "Script Supervisor"
      },
      {
        "name": "Chris O'Hara",
        "department": "Crew",
        "job": "Stunt Coordinator"
      },
      {
        "name": "Jason Ewart",
        "department": "Camera",
        "job": "Steadicam Operator"
      },
      {
        "name": "Frank A. Montaño",
        "department": "Sound",
        "job": "Sound Re-Recording Mixer"
      },
      {
        "name": "Jon Taylor",
        "department": "Sound",
        "job": "Sound Re-Recording Mixer"
      },
      {
        "name": "Tom Partridge",
        "department": "Crew",
        "job": "Visual Effects Editor"
      },
      {
        "name": "Laurent Plancel",
        "department": "Crew",
        "job": "Stunts"
      },
      {
        "name": "Kathy Chasen-Hay",
        "department": "Production",
        "job": "Associate Producer"
      },
      {
        "name": "Hans Bjerno",
        "department": "Camera",
        "job": "Aerial Director of Photography"
      },
      {
        "name": "Christopher Prampin",
        "department": "Lighting",
        "job": "Gaffer"
      },
      {
        "name": "Heather Noble",
        "department": "Art",
        "job": "Assistant Art Director"
      },
      {
        "name": "Sean Haley",
        "department": "Costume & Make-Up",
        "job": "Costumer"
      },
      {
        "name": "Christine Youngstrom",
        "department": "Art",
        "job": "Art Department Coordinator"
      },
      {
        "name": "John Marzano",
        "department": "Camera",
        "job": "Aerial Director of Photography"
      },
      {
        "name": "Adam Dale",
        "department": "Camera",
        "job": "Aerial Director of Photography"
      },
      {
        "name": "Christopher Raphael",
        "department": "Camera",
        "job": "Still Photographer"
      },
      {
        "name": "Ben Dimmock",
        "department": "Crew",
        "job": "Stunts"
      },
      {
        "name": "David Smith",
        "department": "Lighting",
        "job": "Gaffer"
      },
      {
        "name": "Jillian Amburgey",
        "department": "Directing",
        "job": "Script Supervisor"
      },
      {
        "name": "Fraser Taggart",
        "department": "Crew",
        "job": "Second Unit Cinematographer"
      },
      {
        "name": "Fraser Taggart",
        "department": "Camera",
        "job": "Second Unit Director of Photography"
      },
      {
        "name": "David Butler",
        "department": "Costume & Make-Up",
        "job": "Key Costumer"
      },
      {
        "name": "Roxanne Cuenca",
        "department": "Directing",
        "job": "Script Supervisor"
      },
      {
        "name": "Roy Chapman",
        "department": "Art",
        "job": "Property Master"
      },
      {
        "name": "Oliver Loncraine",
        "department": "Camera",
        "job": "Camera Operator"
      },
      {
        "name": "David Malinowski",
        "department": "Costume & Make-Up",
        "job": "Prosthetic Makeup Artist"
      },
      {
        "name": "Carol McConnaughey",
        "department": "Crew",
        "job": "Unit Publicist"
      },
      {
        "name": "Nava R. Sadan",
        "department": "Costume & Make-Up",
        "job": "Costume Supervisor"
      },
      {
        "name": "Christopher Downs",
        "department": "Crew",
        "job": "CG Supervisor"
      },
      {
        "name": "Daniel Leavitt",
        "department": "Crew",
        "job": "Stunts"
      },
      {
        "name": "Choi Ho Man",
        "department": "Art",
        "job": "Art Direction"
      },
      {
        "name": "Tim R. Lafferty",
        "department": "Art",
        "job": "Construction Foreman"
      },
      {
        "name": "Jess Jansen",
        "department": "Editing",
        "job": "Assistant Editor"
      },
      {
        "name": "Dean Bailey",
        "department": "Crew",
        "job": "Stunt Driver"
      },
      {
        "name": "Daniel Graham",
        "department": "Crew",
        "job": "Stunts"
      },
      {
        "name": "Ian Sullivan",
        "department": "Editing",
        "job": "Digital Intermediate"
      },
      {
        "name": "Dominic Hyman",
        "department": "Art",
        "job": "Supervising Art Director"
      },
      {
        "name": "Hiram Garcia",
        "department": "Production",
        "job": "Producer"
      },
      {
        "name": "Remo Tozzi",
        "department": "Art",
        "job": "Art Direction"
      },
      {
        "name": "Nikos Kalimerakis",
        "department": "Lighting",
        "job": "Gaffer"
      },
      {
        "name": "Cristina Waltz",
        "department": "Costume & Make-Up",
        "job": "Key Makeup Artist"
      },
      {
        "name": "Derek Walker",
        "department": "Camera",
        "job": "Camera Operator"
      },
      {
        "name": "Mike Massa",
        "department": "Crew",
        "job": "Stunts"
      },
      {
        "name": "Jessica Phillips",
        "department": "Costume & Make-Up",
        "job": "Costumer"
      },
      {
        "name": "John Flemming",
        "department": "Camera",
        "job": "Key Grip"
      },
      {
        "name": "Dean Foard",
        "department": "Lighting",
        "job": "Lighting Technician"
      },
      {
        "name": "Dominic Ackland-Snow",
        "department": "Art",
        "job": "Construction Manager"
      },
      {
        "name": "Travis Dultz",
        "department": "Editing",
        "job": "3D Editor"
      },
      {
        "name": "Jimmy Hart",
        "department": "Crew",
        "job": "Stunts"
      },
      {
        "name": "Oliver Cubbage",
        "department": "Visual Effects",
        "job": "Visual Effects Supervisor"
      },
      {
        "name": "Daniel Smith",
        "department": "Camera",
        "job": "Still Photographer"
      },
      {
        "name": "Dan Glass",
        "department": "Visual Effects",
        "job": "Visual Effects Supervisor"
      },
      {
        "name": "David Cain",
        "department": "Production",
        "job": "Unit Production Manager"
      },
      {
        "name": "JoJo Williams",
        "department": "Costume & Make-Up",
        "job": "Makeup Artist"
      },
      {
        "name": "Liam Byrne",
        "department": "Crew",
        "job": "Supervising Armorer"
      },
      {
        "name": "Brian Nickels",
        "department": "Crew",
        "job": "Stunts"
      },
      {
        "name": "Matthew A. Petrosky",
        "department": "Camera",
        "job": "Steadicam Operator"
      },
      {
        "name": "John Brubaker",
        "department": "Visual Effects",
        "job": "Compositing Supervisor"
      },
      {
        "name": "Jason Curle",
        "department": "Crew",
        "job": "Stunts"
      },
      {
        "name": "Heidi Moneymaker",
        "department": "Crew",
        "job": "Stunts"
      },
      {
        "name": "Adam Pere",
        "department": "Visual Effects",
        "job": "Visual Effects Producer"
      },
      {
        "name": "Matthew D'Angibau",
        "department": "Visual Effects",
        "job": "Matchmove Supervisor"
      },
      {
        "name": "Oscar Gomez",
        "department": "Lighting",
        "job": "Key Rigging Grip"
      },
      {
        "name": "Barbara Holmes",
        "department": "Crew",
        "job": "Visual Effects Editor"
      },
      {
        "name": "Nick Mitchell",
        "department": "Lighting",
        "job": "Electrician"
      },
      {
        "name": "Marisol Roncali",
        "department": "Production",
        "job": "Casting"
      },
      {
        "name": "Sean Rogers",
        "department": "Camera",
        "job": "Libra Head Technician"
      },
      {
        "name": "Kelly Maracin Krieg",
        "department": "Directing",
        "job": "Script Supervisor"
      },
      {
        "name": "Sam Paul Toms",
        "department": "Crew",
        "job": "Visual Effects Editor"
      },
      {
        "name": "Phong Giang",
        "department": "Crew",
        "job": "Stunts"
      },
      {
        "name": "Jeremy Fry",
        "department": "Crew",
        "job": "Stunts"
      },
      {
        "name": "Harry Lu",
        "department": "Crew",
        "job": "Armorer"
      },
      {
        "name": "Malosi Leonard",
        "department": "Crew",
        "job": "Stunts"
      },
      {
        "name": "Liam McCartney",
        "department": "Crew",
        "job": "Supervising Armorer"
      },
      {
        "name": "Matthew Deetsch",
        "department": "Lighting",
        "job": "Lighting Programmer"
      },
      {
        "name": "John Casali",
        "department": "Sound",
        "job": "Sound Mixer"
      },
      {
        "name": "Richard Burden",
        "department": "Crew",
        "job": "Stunt Driver"
      },
      {
        "name": "David Castillo",
        "department": "Crew",
        "job": "Stunts"
      },
      {
        "name": "Nicole Furia",
        "department": "Production",
        "job": "Associate Producer"
      },
      {
        "name": "Martin Ivanov",
        "department": "Crew",
        "job": "Stunt Driver"
      },
      {
        "name": "Stamos Triantafyllos",
        "department": "Camera",
        "job": "Camera Operator"
      },
      {
        "name": "Fatemeh Khoshkhou",
        "department": "Visual Effects",
        "job": "Visual Effects Producer"
      },
      {
        "name": "Can Aydin",
        "department": "Crew",
        "job": "Stunts"
      },
      {
        "name": "Jason Wasserman",
        "department": "Editing",
        "job": "First Assistant Editor"
      },
      {
        "name": "Chris Morrison",
        "department": "Crew",
        "job": "Stunts"
      },
      {
        "name": "Holland Diaz",
        "department": "Crew",
        "job": "Stunts"
      },
      {
        "name": "Sara Kramer",
        "department": "Costume & Make-Up",
        "job": "Key Makeup Artist"
      },
      {
        "name": "Jean-Paul Ly",
        "department": "Crew",
        "job": "Stunts"
      },
      {
        "name": "Louis Delavenne",
        "department": "Crew",
        "job": "Aerial Coordinator"
      },
      {
        "name": "Chloe Reynolds",
        "department": "Costume & Make-Up",
        "job": "Set Costumer"
      },
      {
        "name": "Kyle McCulloch",
        "department": "Visual Effects",
        "job": "Visual Effects Supervisor"
      },
      {
        "name": "Brionna Maria Lynch",
        "department": "Crew",
        "job": "Stunt Driver"
      },
      {
        "name": "Dave Hussey",
        "department": "Editing",
        "job": "Digital Intermediate Colorist"
      },
      {
        "name": "Sue Chipperton",
        "department": "Crew",
        "job": "Animal Coordinator"
      },
      {
        "name": "Peter Graf",
        "department": "Camera",
        "job": "Aerial Camera Technician"
      },
      {
        "name": "Ralph Malani",
        "department": "Costume & Make-Up",
        "job": "Hairstylist"
      },
      {
        "name": "John Macdonald",
        "department": "Crew",
        "job": "Stunts"
      },
      {
        "name": "Eddie Gomez",
        "department": "Costume & Make-Up",
        "job": "Set Costumer"
      },
      {
        "name": "Steven Blizzard",
        "department": "Camera",
        "job": "Drone Pilot"
      },
      {
        "name": "Cale Schultz",
        "department": "Crew",
        "job": "Stunts"
      },
      {
        "name": "Ryō Murakawa",
        "department": "Costume & Make-Up",
        "job": "Key Hair Stylist"
      },
      {
        "name": "Melody Koerber",
        "department": "Costume & Make-Up",
        "job": "Key Costumer"
      },
      {
        "name": "Bogdan Iofciulescu",
        "department": "Crew",
        "job": "Techno Crane Operator"
      },
      {
        "name": "Andrei Nazarenko",
        "department": "Crew",
        "job": "Stunts"
      },
      {
        "name": "Rachael Evelyn",
        "department": "Crew",
        "job": "Stunts"
      },
      {
        "name": "Anton Agerbo",
        "department": "Visual Effects",
        "job": "Visual Effects Producer"
      },
      {
        "name": "Donny Bailey",
        "department": "Crew",
        "job": "Stunt Driver"
      },
      {
        "name": "Peter Ayriss",
        "department": "Camera",
        "job": "Drone Pilot"
      },
      {
        "name": "Danielle Millington-Peck",
        "department": "Crew",
        "job": "Visual Effects Editor"
      },
      {
        "name": "Danny Wynands",
        "department": "Crew",
        "job": "Stunts"
      },
      {
        "name": "Marc Bitz",
        "department": "Art",
        "job": "Assistant Art Director"
      },
      {
        "name": "Niko Nedyalkov",
        "department": "Crew",
        "job": "Stunt Double"
      },
      {
        "name": "Tom Rodgers",
        "department": "Crew",
        "job": "Stunts"
      },
      {
        "name": "Courtney McClain",
        "department": "Costume & Make-Up",
        "job": "Assistant Costume Designer"
      },
      {
        "name": "Chris Pollard",
        "department": "Crew",
        "job": "Stunts"
      },
      {
        "name": "Liz Oliver",
        "department": "Costume & Make-Up",
        "job": "Ager/Dyer"
      },
      {
        "name": "C.J. Burbage",
        "department": "Visual Effects",
        "job": "Senior Animator"
      },
      {
        "name": "Anis Cheurfa",
        "department": "Crew",
        "job": "Stunts"
      },
      {
        "name": "Axel Akesson",
        "department": "Crew",
        "job": "CG Supervisor"
      },
      {
        "name": "Matt Perrin",
        "department": "Visual Effects",
        "job": "Pre-Visualization Supervisor"
      },
      {
        "name": "Jennie Murphy",
        "department": "Art",
        "job": "Art Department Coordinator"
      },
      {
        "name": "Kathryn Brillhart",
        "department": "Visual Effects",
        "job": "Visual Effects Production Manager"
      },
      {
        "name": "Dani Rose",
        "department": "Camera",
        "job": "Drone Pilot"
      },
      {
        "name": "Mark Hyde",
        "department": "Camera",
        "job": "Key Grip"
      },
      {
        "name": "Charlotte Malynn",
        "department": "Art",
        "job": "Art Direction"
      },
      {
        "name": "Charlotte Malynn",
        "department": "Art",
        "job": "Assistant Art Director"
      },
      {
        "name": "Yu Ying Chien",
        "department": "Crew",
        "job": "Visual Effects Editor"
      },
      {
        "name": "Dan Jones",
        "department": "Lighting",
        "job": "Best Boy Electric"
      },
      {
        "name": "Paige Chaytor",
        "department": "Production",
        "job": "Production Supervisor"
      },
      {
        "name": "Charlie Wyldeck-Flowers",
        "department": "Camera",
        "job": "Key Grip"
      },
      {
        "name": "Jakris Smittant",
        "department": "Visual Effects",
        "job": "Visual Effects Production Manager"
      },
      {
        "name": "Jason Selsor",
        "department": "Lighting",
        "job": "Rigging Grip"
      },
      {
        "name": "Neil Ashton",
        "department": "Lighting",
        "job": "Electrician"
      },
      {
        "name": "Caleb Choo",
        "department": "Visual Effects",
        "job": "Matchmove Supervisor"
      },
      {
        "name": "Mark Fitzgerald",
        "department": "Editing",
        "job": "Additional Editor"
      },
      {
        "name": "Justin Pearson",
        "department": "Crew",
        "job": "Stunt Driver"
      },
      {
        "name": "Dan Godar",
        "department": "Camera",
        "job": "Aerial Camera"
      },
      {
        "name": "Eric Moliner",
        "department": "Visual Effects",
        "job": "Creature Technical Director"
      },
      {
        "name": "Nelson Dsouza",
        "department": "Visual Effects",
        "job": "Visual Effects Production Manager"
      },
      {
        "name": "Chris Milani",
        "department": "Lighting",
        "job": "Lighting Technician"
      },
      {
        "name": "Sianoosh Nasiriziba",
        "department": "Visual Effects",
        "job": "Senior Animator"
      },
      {
        "name": "Michael Brazelton",
        "department": "Visual Effects",
        "job": "Visual Effects Supervisor"
      },
      {
        "name": "Baptiste Chauveau",
        "department": "Visual Effects",
        "job": "Matte Painter"
      },
      {
        "name": "Dimitri Uradovskiy",
        "department": "Visual Effects",
        "job": "2D Supervisor"
      },
      {
        "name": "Pawl Fulker",
        "department": "Visual Effects",
        "job": "Pre-Visualization Supervisor"
      },
      {
        "name": "Josh Sykes",
        "department": "Visual Effects",
        "job": "Visual Effects Producer"
      },
      {
        "name": "Tom Hornsby",
        "department": "Costume & Make-Up",
        "job": "Costume Supervisor"
      },
      {
        "name": "Mike King",
        "department": "Lighting",
        "job": "Electrician"
      },
      {
        "name": "Bryan Ryan",
        "department": "Visual Effects",
        "job": "Visual Effects Production Manager"
      },
      {
        "name": "Lloyd Dudley",
        "department": "Sound",
        "job": "Sound Mixer"
      },
      {
        "name": "Maria Friesen",
        "department": "Editing",
        "job": "3D Editor"
      },
      {
        "name": "David McMillan",
        "department": "Lighting",
        "job": "Lighting Technician"
      },
      {
        "name": "Negoita Mihai",
        "department": "Camera",
        "job": "Libra Head Technician"
      },
      {
        "name": "Paul Sinnott",
        "department": "Costume & Make-Up",
        "job": "Wardrobe Assistant"
      },
      {
        "name": "Andrew Burford",
        "department": "Crew",
        "job": "Stunts"
      },
      {
        "name": "Mario Spanna",
        "department": "Camera",
        "job": "Libra Head Technician"
      },
      {
        "name": "Matthias Winkler",
        "department": "Crew",
        "job": "CG Supervisor"
      },
      {
        "name": "Damien di Toro",
        "department": "Crew",
        "job": "Visual Effects Editor"
      },
      {
        "name": "Sullivan Richard",
        "department": "Visual Effects",
        "job": "Matte Painter"
      },
      {
        "name": "Erica Kim",
        "department": "Lighting",
        "job": "Lighting Technician"
      },
      {
        "name": "Hanny Tjan",
        "department": "Costume & Make-Up",
        "job": "Makeup Artist"
      },
      {
        "name": "Tom Wade",
        "department": "Camera",
        "job": "Camera Operator"
      },
      {
        "name": "King Louie Palomo",
        "department": "Visual Effects",
        "job": "Visual Effects Production Assistant"
      },
      {
        "name": "Makoto Koyama",
        "department": "Visual Effects",
        "job": "Senior Animator"
      },
      {
        "name": "Joel Christopher",
        "department": "Costume & Make-Up",
        "job": "Set Costumer"
      },
      {
        "name": "Fraser Fennell-Ball",
        "department": "Directing",
        "job": "Second Assistant Director"
      },
      {
        "name": "Andy Lister",
        "department": "Crew",
        "job": "Stunts"
      },
      {
        "name": "Bradley Farmer",
        "department": "Crew",
        "job": "Stunt Driver"
      },
      {
        "name": "Felicity Goldsworthy",
        "department": "Costume & Make-Up",
        "job": "Principal Costumer"
      },
      {
        "name": "Tony Lazzara",
        "department": "Crew",
        "job": "Stunts"
      },
      {
        "name": "Warren Hickman",
        "department": "Crew",
        "job": "Visual Effects Editor"
      },
      {
        "name": "Rob Hunt",
        "department": "Crew",
        "job": "Stunts"
      },
      {
        "name": "Peter Lasrado",
        "department": "Crew",
        "job": "CG Supervisor"
      },
      {
        "name": "Jamie Hess",
        "department": "Costume & Make-Up",
        "job": "Makeup Artist"
      },
      {
        "name": "Georgette Sweet",
        "department": "Costume & Make-Up",
        "job": "Hairstylist"
      },
      {
        "name": "Stian Dahlslett",
        "department": "Art",
        "job": "Concept Artist"
      },
      {
        "name": "Benjamin Last",
        "department": "Art",
        "job": "Concept Artist"
      },
      {
        "name": "Renars Latkovskis",
        "department": "Crew",
        "job": "Stunts"
      },
      {
        "name": "Gemma Hoff",
        "department": "Costume & Make-Up",
        "job": "Makeup Artist"
      },
      {
        "name": "Gary Kane",
        "department": "Crew",
        "job": "Stunts"
      },
      {
        "name": "Michael Hugghins",
        "department": "Crew",
        "job": "Stunt Driver"
      },
      {
        "name": "Jordann Aguon",
        "department": "Costume & Make-Up",
        "job": "Makeup Artist"
      },
      {
        "name": "Paul Bailey",
        "department": "Crew",
        "job": "Stunt Driver"
      },
      {
        "name": "Ben Essex",
        "department": "Crew",
        "job": "Stunts"
      },
      {
        "name": "Elizabeth Donker Curtius",
        "department": "Crew",
        "job": "Stunt Double"
      },
      {
        "name": "April Dunlap",
        "department": "Costume & Make-Up",
        "job": "Costumer"
      },
      {
        "name": "Robert Hladik",
        "department": "Crew",
        "job": "Stunts"
      },
      {
        "name": "Julia Strack",
        "department": "Visual Effects",
        "job": "Compositing Supervisor"
      },
      {
        "name": "Nathaniel Perry",
        "department": "Crew",
        "job": "Stunt Double"
      },
      {
        "name": "Josh Milne",
        "department": "Camera",
        "job": "Libra Head Technician"
      },
      {
        "name": "Lucy Cork",
        "department": "Crew",
        "job": "Stunt Double"
      },
      {
        "name": "Sina Ali",
        "department": "Crew",
        "job": "Stunts"
      },
      {
        "name": "Jess Lundgren",
        "department": "Crew",
        "job": "Stunts"
      },
      {
        "name": "Lara Licari",
        "department": "Costume & Make-Up",
        "job": "Makeup Artist"
      },
      {
        "name": "Richard Wheeldon",
        "department": "Crew",
        "job": "Stunts"
      },
      {
        "name": "Liam Carey",
        "department": "Crew",
        "job": "Stunts"
      },
      {
        "name": "John Street",
        "department": "Crew",
        "job": "Stunts"
      },
      {
        "name": "Dan Griffiths",
        "department": "Crew",
        "job": "Stunts"
      },
      {
        "name": "Ian Edwards",
        "department": "Crew",
        "job": "Armorer"
      },
      {
        "name": "Ainsley Davies",
        "department": "Production",
        "job": "Executive Producer"
      },
      {
        "name": "Sarah Evelyn",
        "department": "Costume & Make-Up",
        "job": "Costume Designer"
      },
      {
        "name": "Tom Aldcroft",
        "department": "Camera",
        "job": "Aerial Camera Technician"
      },
      {
        "name": "Soren Bendt Aaboe Pedersen",
        "department": "Art",
        "job": "Storyboard Artist"
      },
      {
        "name": "Katy Bullock",
        "department": "Crew",
        "job": "Stunts"
      },
      {
        "name": "Adam Basil",
        "department": "Crew",
        "job": "Stunts"
      },
      {
        "name": "Kirk A. Jenkins",
        "department": "Crew",
        "job": "Stunts"
      },
      {
        "name": "Pete White",
        "department": "Crew",
        "job": "Stunt Coordinator"
      },
      {
        "name": "Alistair Williams",
        "department": "Visual Effects",
        "job": "Special Effects Supervisor"
      },
      {
        "name": "Ray Valerio",
        "department": "Lighting",
        "job": "Rigging Grip"
      },
      {
        "name": "Adelaide Filippe",
        "department": "Art",
        "job": "Concept Artist"
      },
      {
        "name": "Chris Lees",
        "department": "Art",
        "job": "Concept Artist"
      },
      {
        "name": "Marcos Weiss",
        "department": "Art",
        "job": "Concept Artist"
      },
      {
        "name": "Andrew Naylor",
        "department": "Art",
        "job": "Construction Coordinator"
      },
      {
        "name": "Ermar Alexander",
        "department": "Crew",
        "job": "Stunts"
      },
      {
        "name": "Liam Coote",
        "department": "Crew",
        "job": "Stunts"
      },
      {
        "name": "Phil Arntz",
        "department": "Camera",
        "job": "Aerial Camera"
      },
      {
        "name": "Scott McKee",
        "department": "Camera",
        "job": "Aerial Camera"
      },
      {
        "name": "Stephen Peters",
        "department": "Camera",
        "job": "Drone Pilot"
      },
      {
        "name": "James Clemo",
        "department": "Lighting",
        "job": "Electrician"
      },
      {
        "name": "George Kalimerakis",
        "department": "Lighting",
        "job": "Electrician"
      },
      {
        "name": "John M.H. Lee",
        "department": "Lighting",
        "job": "Electrician"
      },
      {
        "name": "Jim Agnew",
        "department": "Lighting",
        "job": "Electrician"
      },
      {
        "name": "Michele Abramo Puricelli",
        "department": "Camera",
        "job": "Libra Head Technician"
      },
      {
        "name": "Eric Arnold Cortez",
        "department": "Lighting",
        "job": "Lighting Technician"
      },
      {
        "name": "Michael Fennelly",
        "department": "Lighting",
        "job": "Lighting Technician"
      },
      {
        "name": "Ricky Carrillo",
        "department": "Lighting",
        "job": "Rigging Gaffer"
      },
      {
        "name": "Fernando Santaella Navarro",
        "department": "Costume & Make-Up",
        "job": "Key Hair Stylist"
      },
      {
        "name": "Martin Kemble",
        "department": "Production",
        "job": "Production Coordinator"
      },
      {
        "name": "Rohit Chandrashekhar Nair",
        "department": "Production",
        "job": "Production Coordinator"
      },
      {
        "name": "Samantha Arnold",
        "department": "Production",
        "job": "Production Coordinator"
      },
      {
        "name": "Daniel Castle King",
        "department": "Production",
        "job": "Production Coordinator"
      },
      {
        "name": "Harrison Gunnarshaug",
        "department": "Production",
        "job": "Production Secretary"
      },
      {
        "name": "Alex Leung",
        "department": "Production",
        "job": "Production Secretary"
      },
      {
        "name": "Jenny Kissoon",
        "department": "Production",
        "job": "Production Secretary"
      },
      {
        "name": "Frances E. Barer",
        "department": "Costume & Make-Up",
        "job": "Ager/Dyer"
      },
      {
        "name": "Teddy George-Poku",
        "department": "Costume & Make-Up",
        "job": "Assistant Costume Designer"
      },
      {
        "name": "Marianna Bourmpoula",
        "department": "Costume & Make-Up",
        "job": "Costume Assistant"
      },
      {
        "name": "Maia Herzog Lee",
        "department": "Costume & Make-Up",
        "job": "Costume Assistant"
      },
      {
        "name": "Josie May",
        "department": "Costume & Make-Up",
        "job": "Costume Assistant"
      },
      {
        "name": "Robyn Morell",
        "department": "Costume & Make-Up",
        "job": "Costume Assistant"
      },
      {
        "name": "Róisín Straver",
        "department": "Costume & Make-Up",
        "job": "Costume Assistant"
      },
      {
        "name": "Lily Bevan",
        "department": "Costume & Make-Up",
        "job": "Costume Coordinator"
      },
      {
        "name": "George Glasgow",
        "department": "Costume & Make-Up",
        "job": "Costumer"
      },
      {
        "name": "Jeanine McKirnan",
        "department": "Costume & Make-Up",
        "job": "Costumer"
      },
      {
        "name": "Gabriella Morpeth",
        "department": "Costume & Make-Up",
        "job": "Costumer"
      },
      {
        "name": "Aaron Ellis",
        "department": "Costume & Make-Up",
        "job": "Set Costumer"
      },
      {
        "name": "Mia Hope Radford",
        "department": "Costume & Make-Up",
        "job": "Set Costumer"
      },
      {
        "name": "Rajat Chawla",
        "department": "Visual Effects",
        "job": "3D Artist"
      },
      {
        "name": "Tiffany Hall",
        "department": "Visual Effects",
        "job": "3D Generalist"
      },
      {
        "name": "Richard Worsley",
        "department": "Visual Effects",
        "job": "3D Generalist"
      },
      {
        "name": "Sebastian Lauer",
        "department": "Crew",
        "job": "CG Supervisor"
      },
      {
        "name": "Oliver Armstrong",
        "department": "Visual Effects",
        "job": "Compositing Supervisor"
      },
      {
        "name": "Kyle Goodsell",
        "department": "Visual Effects",
        "job": "Compositing Supervisor"
      },
      {
        "name": "Tetu Pawan",
        "department": "Visual Effects",
        "job": "Compositing Supervisor"
      },
      {
        "name": "Joan Buhigas",
        "department": "Visual Effects",
        "job": "Creature Technical Director"
      },
      {
        "name": "Emese Papp",
        "department": "Visual Effects",
        "job": "Creature Technical Director"
      },
      {
        "name": "Anand Kambli",
        "department": "Visual Effects",
        "job": "Creature Technical Director"
      },
      {
        "name": "Etay Herz",
        "department": "Visual Effects",
        "job": "Creature Technical Director"
      },
      {
        "name": "Leona Sharkey",
        "department": "Visual Effects",
        "job": "Creature Technical Director"
      },
      {
        "name": "Matthias Reiche",
        "department": "Visual Effects",
        "job": "Lead Animator"
      },
      {
        "name": "Steve White",
        "department": "Visual Effects",
        "job": "Lead Animator"
      },
      {
        "name": "Mahabub Subhani Shaik",
        "department": "Lighting",
        "job": "Lighting Artist"
      },
      {
        "name": "Taryn Douville",
        "department": "Lighting",
        "job": "Lighting Artist"
      },
      {
        "name": "Argha Sen",
        "department": "Lighting",
        "job": "Lighting Artist"
      },
      {
        "name": "Sujay Kumar G.",
        "department": "Visual Effects",
        "job": "Matchmove Supervisor"
      },
      {
        "name": "Dipak Tarpara",
        "department": "Visual Effects",
        "job": "VFX Artist"
      },
      {
        "name": "Jason Wong",
        "department": "Visual Effects",
        "job": "VFX Artist"
      },
      {
        "name": "Roberta Fischetti",
        "department": "Visual Effects",
        "job": "VFX Editor"
      },
      {
        "name": "Kat Newington",
        "department": "Visual Effects",
        "job": "VFX Production Coordinator"
      },
      {
        "name": "Alicia Abril Carrera",
        "department": "Crew",
        "job": "Visual Effects Editor"
      },
      {
        "name": "Laura El Alam",
        "department": "Crew",
        "job": "Visual Effects Editor"
      },
      {
        "name": "Marlene Nehls",
        "department": "Visual Effects",
        "job": "Visual Effects Producer"
      },
      {
        "name": "Alexa Barros",
        "department": "Visual Effects",
        "job": "Visual Effects Production Assistant"
      },
      {
        "name": "Ben Duffy",
        "department": "Visual Effects",
        "job": "Visual Effects Production Assistant"
      },
      {
        "name": "Hermione Francis",
        "department": "Visual Effects",
        "job": "Visual Effects Production Assistant"
      },
      {
        "name": "Andrew Shawley",
        "department": "Visual Effects",
        "job": "Visual Effects Production Assistant"
      },
      {
        "name": "Sheila Silveira",
        "department": "Visual Effects",
        "job": "Visual Effects Production Assistant"
      },
      {
        "name": "Roni Rodrigues",
        "department": "Visual Effects",
        "job": "Visual Effects Supervisor"
      },
      {
        "name": "Kristin Derella",
        "department": "Editing",
        "job": "Assistant Editor"
      },
      {
        "name": "Miles Anderson",
        "department": "Editing",
        "job": "Colorist"
      },
      {
        "name": "Tom Howard",
        "department": "Lighting",
        "job": "Lighting Programmer"
      },
      {
        "name": "Venice Smith",
        "department": "Crew",
        "job": "Stunts"
      },
      {
        "name": "Pingi Moli",
        "department": "Crew",
        "job": "Stunts"
      },
      {
        "name": "Alvin Chon",
        "department": "Crew",
        "job": "Stunts"
      },
      {
        "name": "Dustin Nelson",
        "department": "Crew",
        "job": "Stunts"
      },
      {
        "name": "Tim Davies",
        "department": "Crew",
        "job": "Stunts"
      },
      {
        "name": "Matt Lange",
        "department": "Sound",
        "job": "Sound Designer"
      },
      {
        "name": "Karen Smithson",
        "department": "Crew",
        "job": "Stunts"
      },
      {
        "name": "Shane Roberts",
        "department": "Crew",
        "job": "Stunts"
      },
      {
        "name": "Tilly Powell",
        "department": "Crew",
        "job": "Stunts"
      },
      {
        "name": "Chris Manger",
        "department": "Crew",
        "job": "Stunts"
      },
      {
        "name": "Bogdan Kumšackij",
        "department": "Crew",
        "job": "Stunts"
      },
      {
        "name": "Tom Cotton",
        "department": "Crew",
        "job": "Stunts"
      },
      {
        "name": "Brandon Cornell",
        "department": "Crew",
        "job": "Utility Stunts"
      },
      {
        "name": "Mauro Calo",
        "department": "Crew",
        "job": "Stunts"
      },
      {
        "name": "Paul Ginns",
        "department": "Crew",
        "job": "Stunts"
      },
      {
        "name": "Joseph Paxton",
        "department": "Crew",
        "job": "Stunts"
      },
      {
        "name": "Benos Noble",
        "department": "Crew",
        "job": "Stunts"
      },
      {
        "name": "Dom Dumaresq",
        "department": "Crew",
        "job": "Stunts"
      },
      {
        "name": "Clayton Grover",
        "department": "Crew",
        "job": "Stunt Driver"
      },
      {
        "name": "Aviv Bar-Ami",
        "department": "Visual Effects",
        "job": "VFX Artist"
      },
      {
        "name": "Alexander T.H. Browne",
        "department": "Visual Effects",
        "job": "VFX Artist"
      },
      {
        "name": "Christoph Westphal",
        "department": "Visual Effects",
        "job": "VFX Artist"
      },
      {
        "name": "Craig Dolby",
        "department": "Crew",
        "job": "Stunts"
      },
      {
        "name": "Nigel Oliver",
        "department": "Crew",
        "job": "Stunts"
      },
      {
        "name": "Rick English",
        "department": "Crew",
        "job": "Stunts"
      },
      {
        "name": "Pete Olivant",
        "department": "Crew",
        "job": "Stunts"
      },
      {
        "name": "Matt Crook",
        "department": "Crew",
        "job": "Stunts"
      },
      {
        "name": "Mark Dobson",
        "department": "Crew",
        "job": "Stunts"
      },
      {
        "name": "Enele Ma'afu Tauteoli",
        "department": "Crew",
        "job": "Stunts"
      },
      {
        "name": "Dan Matteucci",
        "department": "Crew",
        "job": "Stunt Driver"
      },
      {
        "name": "Dave Lovano",
        "department": "Crew",
        "job": "Stunt Driver"
      }
    ]
  },
  "keywords": [
    "london, england",
    "biological weapon",
    "secret organization",
    "family clan",
    "spin off",
    "family reunion",
    "buddy comedy",
    "samoa",
    "aftercreditsstinger",
    "duringcreditsstinger",
    "buddy movie",
    "mother son relationship",
    "father daughter relationship",
    "brother sister relationship"
  ],
  "mpaa": "PG-13",
  "summaries": [
    "Lawman Luke Hobbs and outcast Deckard Shaw form an unlikely alliance when a cyber-genetically enhanced villain threatens the future of humanity."
  ],
  "synopsis": "This stand-alone 'Fast and Furious' film opens in London, England where a team of MI6 agents led by Hattie Shaw (Vanessa Kirby) storm a warehouse to retrieve a deadly virus called \"The Snowflake\". They are found by the super-enhanced Brixton Lore (Idris Elba). Because of his cybernetic augmentations, he is able to sense incoming attacks, which allows him to wipe the floor with all of the other agents. Hattie injects her right hand with the Snowflake and escapes from Brixton's sight. He grabs a radio and makes it seem as though Hattie is a traitor who took the virus for herself.Meanwhile, Luke Hobbs (Dwayne Johnson) and Deckard Shaw (Jason Statham) wake up in their own homes in Los Angeles and London. They go about their daily routines before later going to separate nightclubs to beat the crap out of dozens of goons before they each find one to interrogate. Both Hobbs and Shaw have heard about the super virus that has been going around, and they know it has been manufactured by a terrorist group called Eteon. Their respective goons fail to give them the info they want, so Hobbs tattoos \"I Love Cops\" on his forehead while Shaw leaves his guy dangling out a window.Hobbs has breakfast in a diner with his daughter Sam (Eliana Sua) when he is visited by an old friend/CIA agent Locke (Ryan Reynolds). He informs Hobbs about the Snowflake and just how serious of a threat it is. Although reluctant to help, Hobbs agrees to do so. At the same time, Shaw goes to visit his mother Magdalene, AKA \"Queenie\" (Helen Mirren), in prison. She tells him about Hattie's predicament and that he should reach out to her, but he doesn't think Hattie wants to see him. After leaving the prison, Shaw is approached by Agent Loeb (Rob Delaney) to also go after the Snowflake. This leads Hobbs and Shaw to come face-to-face once again with Locke and Loeb asking them to work together. Their response? \"No FUCKING way!\" After exchanging insults, the two begrudgingly agree to work together. The other agents track Hattie down for the guys to go after her.While Shaw goes to Hattie's booby-trapped home, Hobbs manages to find her on the streets. She fights Hobbs to get away, while Shaw is fought by agents trying to track Hattie. He beats them all across the room, while Hobbs manages to gain the upper hand and bring Hattie in.Hattie is taken back to the CIA headquarters for questioning by Hobbs. Shaw shows up and informs Hobbs that she is his sister. She tells them that she is carrying the virus, just before Brixton shows up and attacks. Shaw recognizes him as an old colleague that he supposedly killed years earlier. Brixton attempts to take Hattie with him by going down the building with a harness, but Hobbs and Shaw pursue. Hobbs slides down the harness to get rid of Brixton's goons before giving Hattie a chance to get away. Hobbs fights Brixton, only to discover he is no match for the superhuman. Shaw drives by to pick up Hobbs and Hattie, and Brixton chases after them on a motorcycle, but the heroes lose him after he crashes through a bus. The three then see that Eteon has manipulated the media into declaring them all fugitives and traitors. Hattie goes off to try and find Professor Andreiko (Eddie Marsan), the creator of the Snowflake and the one who can extract the virus from her. Hobbs shows that he was tracking Andreiko before the attack, and they manage to locate him at a newsstand.Brixton returns to Eteon's headquarters to get more juiced up. He speaks to Eteon's mysterious leader, who knows of both Hobbs and Shaw and wants Brixton to have them join Eteon.The trio talk to Andreiko, who says that he developed Snowflake for Eteon, but he left them after realizing their plan to use it on humanity and then force them to be fixed by Eteon. He tells them that the only way to get it out of Hattie is to kill her or extract it from her through a facility in the Ukraine. Shaw uses some of his own gear to help keep himself, Hattie, and Hobbs from being tracked or recognized. They head to Moscow using fake names, with Hobbs getting \"Mike Oxmaul\" and almost getting detained for it. While on the plane, Shaw tells Hobbs to back off of Hattie since he can tell that he is attracted to her. Hobbs taunts Shaw with the prospect of him hooking up with his sister, but their bickering wakes up the air marshal, Dinkley (Kevin Hart). He figures that the two are on a mission, and he bemoans his lack of action. Dinkley gives them his card for whenever they need something.In Moscow, the trio visit an old flame of Shaw's, Margarita, AKA Madame M (Eiza Gonzalez), who is the leader of an all-female crew of criminals that rob peoples homes. She provides them with weapons and gear that they need to storm the Eteon facility. Margarita then takes them to the facility where she makes it look like she is giving Hattie up to Brixton, who is already there after interrogating Andreiko. Hobbs and Shaw sneak their way around the place after dropping in from a jet. They encounter armed goons and proceed to pummel all of them in separate halls. They then use the unconscious goons to get inside, where they are greeted by dozens of armed Eteon agents. Both of them are captured and strapped to electrical cables for interrogation. Brixton tries to get them to join Eteon, with each additional shock coming closer to killing them. Hattie sneaks up on Brixton and almost kills him, but the gun she's holding requires an identity reader. Hobbs and Shaw get free, fight off more goons, and destroy the facility after retrieving the extraction device. Unfortunately, Brixton snaps Andreiko's neck and gets away again, and the device gets wrecked. Hobbs then figures out somewhere to lay low.The three travel to Samoa, Hobbs's childhood home where his estranged family lives. He returns to his mother Sefina (Lori Pelenisa Tuisano) and brothers Jonah (Cliff Curtis), Mateo (Roman Reigns), Timo (Josh Mauga), and Kal (John Tui), plus his three cousins. Jonah is especially dismayed to see Hobbs after his long absence. However, Sefina knows how urgent it is that the brothers help Hobbs out. They go to arm themselves as they prepare for Brixton and Eteon's goons to arrive, but Sefina has gotten rid of all their weapons. The plan then becomes that the family will fight Eteon with their bare hands and wits. Jonah fixes the device to start getting it out of Hattie.Brixton and Eteon are tracked as they make their way to the island. The Hobbs men stand ready for battle. The Eteon goons try to shoot them, but Hattie has disabled their guns. Fists begin to fly, bodies are thrown, and bones are broken as the agents are demolished by the Samoans. Brixton grabs Hattie and starts to escape on a helicopter. Hobbs and Shaw ride together while Jonah and the others follow. They hook their vehicles together like a train as Hobbs throws a hook onto the helicopter to bring it down. The helicopter crashes down below. Hobbs and Shaw face off against Brixton while Hattie has all of the Snowflake removed from her, and she kills Brixton's goon. Realizing he is just going to intercept their every move, Hobbs and Shaw resolve to fight him by having one of them take a hit while the other delivers a hit. This proves effective, as it causes Brixton's programming to overload. After witnessing his defeat, the Eteon leader deprograms Brixton's enhancements, and he dies before falling over the edge of the cliff. The unseen Eteon leader then speaks to Hobbs and Shaw, implying that they will see the two of them again.Afterwards, Shaw and Hattie go visit their mother in prison and leave her a cake that may contain something that will allow her to escape. Meanwhile, Hobbs decides to bring Sam to meet his family, as he has decided to stick around this time.During the credits, Locke contacts Hobbs again as he is fighting with other Eteon agents over another, possibly even more deadly virus. Locke also managed to stab a guy with a brick. In another scene, Hobbs gets Shaw back for the Moscow fake name by having the police get him and address him as \"Hugh Janus\". Shaw steps out but doesn't look like he's going to go quietly."
}