{
  "backdrop_path": "https://image.tmdb.org/t/p/w500/aLqtWLA6NQHBwQHvHDq5z4EKUm0.jpg",
  "id": 533514,
  "title": "Violet Evergarden: The Movie",
  "poster_path": "https://image.tmdb.org/t/p/w500/fwSonK8WrAEqWY7sqjvGRCgzIij.jpg",
  "release_date": "2020-09-18",
  "vote_average": 8.293,
  "popularity": 27.661,
  "overview": "As the world moves on from the war and technological advances bring changes to her life, Violet still hopes to see her lost commanding officer again.",
  "imdb_id": "tt8652818",
  "budget": 0,
  "homepage": "https://www.netflix.com/title/81193214",
  "revenue": 20339624,
  "runtime": 140,
  "genres": [
    "Animation",
    "Fantasy",
    "Romance",
    "Drama"
  ],
  "summaries": [
    "After the aftermath of a war, a young girl who was used as a 'tool' for war learned to live. With the scars of burns, she goes back to her past to feel the true feelings of the Major's, \"I love you.\""
  ],
  "synopsis": ""
}